shaft_cli/__init__.py
shaft_cli/cli.py
shaftengine-1.0.0.dist-info/METADATA
shaftengine-1.0.0.dist-info/WHEEL
shaftengine-1.0.0.dist-info/entry_points.txt
shaftengine-1.0.0.dist-info/top_level.txt
shaftengine-1.0.0.dist-info/RECORD
