Metadata-Version: 2.4
Name: shaftengine
Version: 1.0.0
Requires-Dist: click
Dynamic: requires-dist
